{
  "id": "cosmoshk",
  "name": "cosmoshk",
  "layouts": {
    "default_layout": {
      "name": "default_layout",
      "layout": [
        { "row":  5, "col":  0, "x":  0, "y":  1 },
        { "row":  5, "col":  1, "x":  1, "y":  1 },
        { "row":  5, "col":  2, "x":  2, "y":  1 },
        { "row":  5, "col":  3, "x":  3, "y":  1 },
        { "row":  5, "col":  4, "x":  4, "y":  1 },
        { "row":  5, "col":  5, "x":  5, "y":  1 },
        { "row":  5, "col":  9, "x": 10, "y":  1 },
        { "row":  5, "col": 10, "x": 11, "y":  1 },
        { "row":  5, "col": 11, "x": 12, "y":  1 },
        { "row":  5, "col": 12, "x": 13, "y":  1 },
        { "row":  5, "col": 13, "x": 14, "y":  1 },
        { "row":  5, "col": 14, "x": 15, "y":  1 },

        { "row":  6, "col":  0, "x":  0, "y":  2 },
        { "row":  6, "col":  1, "x":  1, "y":  2 },
        { "row":  6, "col":  2, "x":  2, "y":  2 },
        { "row":  6, "col":  3, "x":  3, "y":  2 },
        { "row":  6, "col":  4, "x":  4, "y":  2 },
        { "row":  6, "col":  5, "x":  5, "y":  2 },
        { "row":  6, "col":  9, "x": 10, "y":  2 },
        { "row":  6, "col": 10, "x": 11, "y":  2 },
        { "row":  6, "col": 11, "x": 12, "y":  2 },
        { "row":  6, "col": 12, "x": 13, "y":  2 },
        { "row":  6, "col": 13, "x": 14, "y":  2 },
        { "row":  6, "col": 14, "x": 15, "y":  2 },

        { "row":  7, "col":  0, "x":  0, "y":  3 },
        { "row":  7, "col":  1, "x":  1, "y":  3 },
        { "row":  7, "col":  2, "x":  2, "y":  3 },
        { "row":  7, "col":  3, "x":  3, "y":  3 },
        { "row":  7, "col":  4, "x":  4, "y":  3 },
        { "row":  7, "col":  5, "x":  5, "y":  3 },
        { "row":  7, "col":  9, "x": 10, "y":  3 },
        { "row":  7, "col": 10, "x": 11, "y":  3 },
        { "row":  7, "col": 11, "x": 12, "y":  3 },
        { "row":  7, "col": 12, "x": 13, "y":  3 },
        { "row":  7, "col": 13, "x": 14, "y":  3 },
        { "row":  7, "col": 14, "x": 15, "y":  3 },

        { "row":  8, "col":  2, "x":  2, "y":  4 },
        { "row":  8, "col":  3, "x":  3, "y":  4 },
        { "row":  8, "col": 11, "x": 12, "y":  4 },
        { "row":  8, "col": 12, "x": 13, "y":  4 },

        { "row":  9, "col":  4, "x":  4.5, "y":  5, "h": 1.5, "r":  15, "rx": 5.5, "ry": 4.4},
        { "row":  9, "col":  5, "x":  5.5, "y":  5, "h": 1.5, "r":  15, "rx": 5.5, "ry": 4.4},
        { "row":  9, "col":  9, "x":  9.5, "y":  5, "h": 1.5, "r":  -15, "rx": 10.5, "ry": 4.4},
        { "row":  9, "col": 10, "x":  10.5, "y":  5, "h": 1.5, "r":  -15, "rx": 10.5, "ry": 4.4},

        { "row": 10, "col":  5, "x":  6, "y": 7, "r":  15, "rx": 5.5, "ry": 4.4},
        { "row": 10, "col":  6, "x":  7, "y": 7, "r":  15, "rx": 5.5, "ry": 4.4},
        { "row": 10, "col":  8, "x":  8, "y": 7, "r":  -15, "rx": 10.5, "ry": 4.4},
        { "row": 10, "col":  9, "x":  9, "y": 7, "r":  -15, "rx": 10.5, "ry": 4.4 },

        { "row": 11, "col":  5, "x":  6, "y": 8, "r":  15, "rx": 5.5, "ry": 4.4},
        { "row": 11, "col":  6, "x":  7, "y": 8, "r":  15, "rx": 5.5, "ry": 4.4},
        { "row": 11, "col":  8, "x":  8, "y": 8, "r":  -15, "rx": 10.5, "ry": 4.4},
        { "row": 11, "col":  9, "x":  9, "y": 8, "r":  -15, "rx": 10.5, "ry": 4.4}
      ]
    }
  },
  "sensors": []
}